[
  {
    "id": "LQx0P",
    "txt": "Nina",
    "isDone": false,
    "creator": "Popo",
    "createdAt": 1598869998510
  },
  {
    "id": "TkI6w",
    "txt": "Do That111",
    "isDone": false,
    "createdAt": 1598868958465,
    "updatedAt": 1598868976534
  },
  {
    "id": "rAbok",
    "txt": "Do it now!",
    "isDone": true,
    "updatedAt": 1598868754699
  },
  {
    "id": "t101",
    "txt": "Wash the dishes",
    "isDone": false
  },
  {
    "id": "tmE",
    "txt": "ido ido",
    "priority": "3",
    "category": "grociries",
    "backgroundColor": "#f71818"
  },
  {
    "id": "CC6",
    "txt": "asdasd",
    "priority": "2",
    "category": "Kids CHugim",
    "backgroundColor": "#7c6e6e",
    "name": "asdasd"
  },
  {
    "id": "QpU",
    "txt": "sdsdsd",
    "priority": "3",
    "category": "Kids CHugim",
    "backgroundColor": "#d23232",
    "name": "idodo"
  },
  {
    "id": "a0L",
    "txt": "idododo",
    "isDone": "true",
    "priority": "2",
    "category": "Home",
    "backgroundColor": "#b28815"
  },
  {
    "id": "NyI",
    "txt": "asdasd",
    "priority": "2",
    "category": "grociries",
    "backgroundColor": "#b68686"
  },
  {
    "id": "zxs",
    "txt": "idooren",
    "priority": "2",
    "category": "Kids CHugim",
    "backgroundColor": "#4c2eb8"
  },
  {
    "id": "MFi",
    "txt": "ddddd",
    "priority": "1",
    "category": "grociries",
    "backgroundColor": "#c09696",
    "name": "puki puki"
  },
  {
    "id": "rmZ",
    "txt": "ffffff",
    "isDone": "true",
    "priority": "1",
    "category": "",
    "backgroundColor": "#000000"
  },
  {
    "id": "SLn",
    "txt": "dsds",
    "priority": "1",
    "category": "Home",
    "backgroundColor": "#000000",
    "name": "sdsd"
  }
]